[
    {
        "id":1,
        "title": "post1",
        "text": "Вічність? Одиниця обчислення часу."
    },
    {
        "id":2,
        "title": "post1",
        "text": "У світі вічно лише тимчасове."
    },
    {
        "id":3,
        "title": "post1",
        "text": "-Час минає? -Час вічно, проходьте Ви!"
    },
    {
        "id":4,
        "title": "post1",
        "text": "Жінки дуже віддані тим, хто їх любить, навіть після смерті… Вони знають, що таке ЛЮБОВ…"
    },
    {
        "id":5,
        "title": "post1",
        "text": "Якби ми жили вічно, як би ми набридли… самим собі!"
    }
]